flashcards/__init__.py
flashcards/__main__.py
flashcards/cli.py
flashcards/flashcards.py
flashcards/python_flashcards.egg-info/PKG-INFO
flashcards/python_flashcards.egg-info/SOURCES.txt
flashcards/python_flashcards.egg-info/dependency_links.txt
flashcards/python_flashcards.egg-info/entry_points.txt
flashcards/python_flashcards.egg-info/not-zip-safe
flashcards/python_flashcards.egg-info/requires.txt
flashcards/python_flashcards.egg-info/top_level.txt
python_flashcards-0.3.0.dist-info/AUTHORS.rst
python_flashcards-0.3.0.dist-info/LICENSE
python_flashcards-0.3.0.dist-info/METADATA
python_flashcards-0.3.0.dist-info/WHEEL
python_flashcards-0.3.0.dist-info/entry_points.txt
python_flashcards-0.3.0.dist-info/top_level.txt
python_flashcards-0.3.0.dist-info/RECORD
