Metadata-Version: 2.1
Name: python-flashcards
Version: 0.3.0
Summary: small cli tool to study using flashcards
Home-page: https://github.com/woile/flashcards
Author: Santiago Fraire Willemoes
Author-email: santiwilly@gmail.com
License: MIT
Keywords: flashcards
Platform: UNKNOWN
Classifier: Development Status :: 5 - Production/Stable
Classifier: Intended Audience :: Developers
Classifier: License :: OSI Approved :: BSD License
Classifier: Operating System :: Unix
Classifier: Operating System :: POSIX
Classifier: Programming Language :: Python
Classifier: Programming Language :: Python :: 2.7
Classifier: Programming Language :: Python :: 3
Classifier: Programming Language :: Python :: 3.3
Classifier: Programming Language :: Python :: 3.4
Classifier: Programming Language :: Python :: 3.5
Classifier: Programming Language :: Python :: 3.6
Classifier: Programming Language :: Python :: Implementation :: CPython
Classifier: Programming Language :: Python :: Implementation :: PyPy
Classifier: Topic :: Utilities
Requires-Dist: PyYAML (==3.12)
Requires-Dist: future (==0.16.0)
